MANIFEST.in
README.md
setup.py
denv/__init__.py
denv.egg-info/PKG-INFO
denv.egg-info/SOURCES.txt
denv.egg-info/dependency_links.txt
denv.egg-info/entry_points.txt
denv.egg-info/top_level.txt