Metadata-Version: 1.0
Name: denv
Version: 1.1.1
Summary: runs commands with env stored in dotfile
Home-page: https://github.com/trustpilot/python-denv
Author: sloev
Author-email: jgv@trustpilot.com
License: MIT
Platform: UNKNOWN
